{
    "flower": "mekanism:block_refined_glowstone",
    "lore": "Through the Osmium Compressor, this bee will produce Refined Glowstone",
    "loreColor": "#ff66cc",
    "sizeModifier": 1,
    "maxTimeInHive": 2400,
    "hasHoneycomb": true,
    "apiaryOutputAmounts": [
      4,
      8,
      32,
      64
    ],
    "apiaryOutputTypes": [
      "COMB",
      "COMB",
      "COMB",
      "COMB",
      "COMB"
    ],
    "auraRange": 20,
    "traits": ["sedimentary", "can_swim"],
    "baseLayerTexture": "metals/refined_glowstone/refined_glowstone",
    "ColorData": {
    "honeycombColor": "#ffbc5e"
    },
    "CombatData": {
      "isPassive": false,
      "removeStingerOnAttack": false,
      "inflictsPoison": true,
      "baseHealth": 20,
      "attackDamage": 4
    },
    "CentrifugeData": {
      "hasCentrifugeOutput": true,

      "mainOutput": "mekanism:nugget_refined_glowstone",
      "mainOutputWeight": 0.6,
      "mainOutputCount": 3,

      "bottleOutput": "resourcefulbees:refined_glowstone_honey_bottle",
      "bottleOutputWeight": 0.07,
      "bottleOutputCount": 1,

      "mainInputCount": 1
    },
    "SpawnData": {
      "canSpawnInWorld": false
    },
    "BreedData": {
      "isBreedable": false
    },
    "TraitData": {
      "hasTraits": true
    }
  }
